search/__init__.py
search/admin.py
search/mixins.py
search/models.py
search/tests.py
search/views.py
search/views_functions.py
search/locale/it/LC_MESSAGES/django.mo
search/locale/it/LC_MESSAGES/django.po
search/migrations/__init__.py
search/static/search/css/datepicker3.css
search/static/search/css/search.css
search/static/search/js/clipboard.min.js
search/static/search/js/js.cookie.js
search/static/search/js/search.js
search/static/search/js/bootstrap-datepicker/bootstrap-datepicker.it.js
search/static/search/js/bootstrap-datepicker/bootstrap-datepicker.js
search/templates/search/_multiple_edit_count.html
search/templates/search/_multiple_edit_results.html
search/templates/search/_searchfield.html
search/templates/search/search.html
search/templatetags/__init__.py
search/templatetags/dumpjson.py
django_multisearch-1.3.0.dist-info/LICENSE.txt
django_multisearch-1.3.0.dist-info/METADATA
django_multisearch-1.3.0.dist-info/WHEEL
django_multisearch-1.3.0.dist-info/top_level.txt
django_multisearch-1.3.0.dist-info/RECORD
