Metadata-Version: 2.1
Name: django-multisearch
Version: 1.3.0
Summary: Multifield search for Django, using Bootstrap 3 and jQuery DataTables
Home-page: https://github.com/baxeico/django-multisearch
Author: Augusto Destrero
Author-email: a.destrero@gmail.com
License: MIT
Keywords: django,search
License-File: LICENSE.txt
Requires-Dist: six>=1.11
